tria.py
src/chunker.py
src/data_models.py
src/git_analyzer.py
src/parsers.py
src/readers.py
src/writers.py
tria-0.4.3.dist-info/licenses/LICENSE
tria-0.4.3.dist-info/METADATA
tria-0.4.3.dist-info/WHEEL
tria-0.4.3.dist-info/entry_points.txt
tria-0.4.3.dist-info/top_level.txt
tria-0.4.3.dist-info/RECORD
