Metadata-Version: 2.4
Name: tria
Version: 0.4.3
Summary: Turn repositories into AI-friendly summaries
Author-email: yegekucuk <yegekucuk@gmail.com>
License-Expression: MIT
Project-URL: Homepage, https://github.com/yegekucuk/tria
Project-URL: Documentation, https://github.com/yegekucuk/tria#readme
Project-URL: Repository, https://github.com/yegekucuk/tria
Project-URL: Issues, https://github.com/yegekucuk/tria/issues
Keywords: git,repository,summarization,ai,llm,markdown,json,xml
Classifier: Development Status :: 3 - Alpha
Classifier: Intended Audience :: Developers
Classifier: Operating System :: OS Independent
Classifier: Programming Language :: Python :: 3
Classifier: Programming Language :: Python :: 3.8
Classifier: Programming Language :: Python :: 3.9
Classifier: Programming Language :: Python :: 3.10
Classifier: Programming Language :: Python :: 3.11
Classifier: Topic :: Software Development :: Documentation
Classifier: Topic :: Software Development :: Version Control :: Git
Requires-Python: >=3.8
License-File: LICENSE
Requires-Dist: pathspec>=0.11.0
Requires-Dist: markdown-it-py>=3.0.0
Provides-Extra: full
Requires-Dist: typer>=0.9.0; extra == "full"
Requires-Dist: rich>=13.0; extra == "full"
Requires-Dist: gitpython>=3.1.0; extra == "full"
Requires-Dist: pyyaml>=6.0; extra == "full"
Dynamic: license-file
